scarplet/WindowedTemplate.py
scarplet/__init__.py
scarplet/core.py
scarplet/dem.py
scarplet/utils.py
scarplet/datasets/__init__.py
scarplet/datasets/base.py
scarplet/datasets/data/carrizo.tif
scarplet/datasets/data/faultzone.tif
scarplet/datasets/data/grandcanyon.tif
scarplet/datasets/data/synthetic.tif
scarplet/tests/__init__.py
scarplet/tests/context.py
scarplet/tests/test_WindowedTemplate.py
scarplet/tests/test_core.py
scarplet/tests/test_dem.py
scarplet-0.1.3.dist-info/DESCRIPTION.rst
scarplet-0.1.3.dist-info/METADATA
scarplet-0.1.3.dist-info/RECORD
scarplet-0.1.3.dist-info/WHEEL
scarplet-0.1.3.dist-info/metadata.json
scarplet-0.1.3.dist-info/top_level.txt
