Metadata-Version: 2.0
Name: scarplet
Version: 0.1.3
Summary: A Python package for topographic template matching
Home-page: https://github.com/rmsare/scarplet
Author: ['Robert Sare', 'George Hilley']
Author-email: rmsare@stanford.edu
License: MIT
Platform: UNKNOWN
Classifier: Development Status :: 4 - Beta
Classifier: Intended Audience :: Developers
Classifier: Intended Audience :: Science/Research
Classifier: Programming Language :: Python :: 3
Classifier: License :: OSI Approved :: MIT License
Classifier: Operating System :: OS Independent
Requires-Dist: gdal
Requires-Dist: matplotlib
Requires-Dist: numexpr
Requires-Dist: numpy
Requires-Dist: pyfftw
Requires-Dist: rasterio
Requires-Dist: scipy
